dnptools/.gitignore
dnptools/__init__.py
dnptools/scoringservice.py
dnptools-0.0.4.dist-info/METADATA
dnptools-0.0.4.dist-info/WHEEL
dnptools-0.0.4.dist-info/licenses/LICENSE
dnptools-0.0.4.dist-info/RECORD
