Metadata-Version: 2.1
Name: dnptools
Version: 0.0.4
Summary: Python utilities for working with DENOPTIM (https://github.com/denoptim-project/DENOPTIM)
Author: David Grellscheid, Marco Foscato, Marcello Costamagna
License-File: LICENSE
Classifier: License :: OSI Approved :: GNU Affero General Public License v3 or later (AGPLv3+)
Classifier: Operating System :: OS Independent
Classifier: Programming Language :: Python :: 3
Requires-Python: >=3.7
